MANIFEST.in
README.txt
setup.cfg
setup.py
c2/__init__.py
c2.patch.filenamenormalizer.egg-info/PKG-INFO
c2.patch.filenamenormalizer.egg-info/SOURCES.txt
c2.patch.filenamenormalizer.egg-info/dependency_links.txt
c2.patch.filenamenormalizer.egg-info/entry_points.txt
c2.patch.filenamenormalizer.egg-info/namespace_packages.txt
c2.patch.filenamenormalizer.egg-info/not-zip-safe
c2.patch.filenamenormalizer.egg-info/requires.txt
c2.patch.filenamenormalizer.egg-info/top_level.txt
c2/patch/__init__.py
c2/patch/filenamenormalizer/__init__.py
c2/patch/filenamenormalizer/config.py
c2/patch/filenamenormalizer/configure.zcml
c2/patch/filenamenormalizer/monkey.py
c2/patch/filenamenormalizer/tests.py
c2/patch/filenamenormalizer/version.txt
docs/HISTORY.txt
docs/INSTALL.txt
docs/LICENSE.GPL
docs/LICENSE.txt