Metadata-Version: 1.0
Name: c2.patch.filenamenormalizer
Version: 1.0b3
Summary: This patch product is for downloaded filename become strange ascii code in muluti-byte languages on Plone
Home-page: http://www.cmscom.jp
Author: Manabu Terada
Author-email: terada@cmscom.jp
License: GPL
Keywords: Plone Patch Japanese normalizer
Platform: UNKNOWN
Classifier: Framework :: Plone
Classifier: Programming Language :: Python
Classifier: Topic :: Software Development :: Libraries :: Python Modules
